track/__init__.py
track/client.py
track/const.py
track/consumer.py
track/request.py
track/utils.py
track/version.py
track/tests/__init__.py
interakt_track_python-1.0.7.dist-info/LICENSE
interakt_track_python-1.0.7.dist-info/METADATA
interakt_track_python-1.0.7.dist-info/WHEEL
interakt_track_python-1.0.7.dist-info/top_level.txt
interakt_track_python-1.0.7.dist-info/RECORD
