Metadata-Version: 2.1
Name: interakt-track-python
Version: 1.0.7
Summary: The easy way to integrate track apis for interakt
Home-page: https://github.com/interakt/track-python
Author: Amar Jaiswal
Author-email: amar.j@cawstudios.com
Maintainer: interakt.ai
License: MIT License
Keywords: INTERAKT,KIWI
Platform: UNKNOWN
Classifier: Development Status :: 4 - Beta
Classifier: Intended Audience :: Developers
Classifier: Topic :: Software Development :: Build Tools
Classifier: License :: OSI Approved :: MIT License
Classifier: Operating System :: OS Independent
Classifier: Programming Language :: Python :: 3.6
Classifier: Programming Language :: Python :: 3.7
Classifier: Programming Language :: Python :: 3.8
Provides-Extra: test
